{"nodes": [{"id": "app_config_server_config", "label": "Server ApplicationConfig (config)", "file_type": "code", "source_file": "src/app/app.config.server.ts", "source_location": null, "source_url": null, "captured_at": null, "author": null, "contributor": null}], "edges": [{"source": "app_config_server_config", "target": "app_config_appconfig", "relation": "references", "confidence": "EXTRACTED", "confidence_score": 1.0, "source_file": "src/app/app.config.server.ts", "source_location": null, "weight": 1.0}, {"source": "app_config_server_config", "target": "app_routes_server_serverroutes", "relation": "references", "confidence": "EXTRACTED", "confidence_score": 1.0, "source_file": "src/app/app.config.server.ts", "source_location": null, "weight": 1.0}, {"source": "app_config_server_config", "target": "app_config_appconfig", "relation": "semantically_similar_to", "confidence": "INFERRED", "confidence_score": 0.85, "source_file": "src/app/app.config.server.ts", "source_location": null, "weight": 0.85}], "hyperedges": [{"id": "ssr_bootstrap_pipeline", "label": "SSR bootstrap pipeline", "nodes": ["main_server_bootstrap", "app_config_server_config", "app_config_appconfig", "app_routes_server_serverroutes", "server_app"], "relation": "participate_in", "confidence": "INFERRED", "confidence_score": 0.85, "source_file": "src/app/app.config.server.ts"}]}